{
  "minecraft:recipes/building_blocks/smooth_quartz_slab_from_smooth_quartz_stonecutting": {
    "criteria": {
      "has_smooth_quartz": "2021-03-13 12:15:32 +0100"
    },
    "done": true
  },
  "minecraft:recipes/building_blocks/smooth_quartz_slab": {
    "criteria": {
      "has_smooth_quartz": "2021-03-13 12:15:32 +0100"
    },
    "done": true
  },
  "minecraft:recipes/brewing/cauldron": {
    "criteria": {
      "has_water_bucket": "2021-03-12 14:27:53 +0100"
    },
    "done": true
  },
  "minecraft:recipes/building_blocks/smooth_quartz_stairs_from_smooth_quartz_stonecutting": {
    "criteria": {
      "has_smooth_quartz": "2021-03-13 12:15:32 +0100"
    },
    "done": true
  },
  "minecraft:adventure/adventuring_time": {
    "criteria": {
      "minecraft:plains": "2021-03-12 13:10:08 +0100"
    },
    "done": false
  },
  "minecraft:recipes/building_blocks/smooth_quartz_stairs": {
    "criteria": {
      "has_smooth_quartz": "2021-03-13 12:15:32 +0100"
    },
    "done": true
  },
  "DataVersion": 2586
}